devstream_client/__init__.py
devstream_client/client.py
devstream_client-0.1.0.dist-info/METADATA
devstream_client-0.1.0.dist-info/WHEEL
devstream_client-0.1.0.dist-info/top_level.txt
devstream_client-0.1.0.dist-info/RECORD
